[
  {
    "id": "1",
    "name": "盘古拓展集团",
    "color": "#FF6B35"
  },
  {
    "id": "2",
    "name": "诺玛运输集团",
    "color": "#00D68F"
  },
  {
    "id": "3",
    "name": "雷火科技公司",
    "color": "#4A9EFF"
  },
  {
    "id": "4",
    "name": "海雷丁家族",
    "color": "#FFD700"
  },
  {
    "id": "5",
    "name": "神圣群星帝国",
    "color": "#9B59B6"
  },
  {
    "id": "6",
    "name": "安东尼奥斯财团",
    "color": "#3498DB"
  },
  {
    "id": "7",
    "name": "未央公约组织",
    "color": "#2ECC71"
  },
  {
    "id": "8",
    "name": "木星工业集团",
    "color": "#E74C3C"
  },
  {
    "id": "9",
    "name": "流放者组织",
    "color": "#FF6B35"
  }
]